backend_api/__init__.py
backend_api/exceptions.py
backend_api/main.py
backend_api/api/__init__.py
backend_api/api/v1/__init__.py
backend_api/api/v1/analysis.py
backend_api/api/v1/api_keys.py
backend_api/api/v1/credit_requests.py
backend_api/api/v1/credits.py
backend_api/api/v1/incidents.py
backend_api/api/v1/logging.py
backend_api/api/v1/metrics.py
backend_api/api/v1/users.py
backend_api/core/__init__.py
backend_api/core/auth.py
backend_api/core/config.py
backend_api/core/database.py
backend_api/core/mongodb.py
backend_api/models/__init__.py
backend_api/models/database.py
backend_api/models/mongodb_models.py
backend_api/models/schemas.py
backend_api/services/CREDIT_SYSTEM.md
backend_api/services/__init__.py
backend_api/services/advanced_bias.py
backend_api/services/advanced_jailbreak.py
backend_api/services/bias.py
backend_api/services/credit_manager.py
backend_api/services/custom_classifiers.py
backend_api/services/custom_toxicity.py
backend_api/services/enhanced_bias.py
backend_api/services/explainability.py
backend_api/services/hallucination.py
backend_api/services/jailbreak.py
backend_api/services/mongodb_credit_manager.py
backend_api/services/policy_engine.py
backend_api/services/remediation.py
backend_api/services/toxicity.py
equitas_sdk/__init__.py
equitas_sdk/client.py
equitas_sdk/exceptions.py
equitas_sdk/models.py
equitas-2.0.3.dist-info/METADATA
equitas-2.0.3.dist-info/WHEEL
equitas-2.0.3.dist-info/licenses/LICENSE
equitas-2.0.3.dist-info/RECORD
