Metadata-Version: 2.4
Name: equitas
Version: 2.0.3
Summary: Equitas: AI Safety & Observability Platform
Project-URL: Homepage, https://github.com/aryan4codes/Equitas
Project-URL: Documentation, https://github.com/aryan4codes/Equitas#readme
Project-URL: Repository, https://github.com/aryan4codes/Equitas
Project-URL: Issues, https://github.com/aryan4codes/Equitas/issues
Author-email: Aryan Rajpurkar <av.rajpurkar@gmail.com>
Maintainer-email: Aryan Rajpurkar <av.rajpurkar@gmail.com>
License: MIT
License-File: LICENSE
Keywords: ai-observability,ai-safety,bias-detection,content-moderation,jailbreak-detection,llm-security,openai,toxicity-detection
Classifier: Development Status :: 3 - Alpha
Classifier: Intended Audience :: Developers
Classifier: License :: OSI Approved :: MIT License
Classifier: Programming Language :: Python :: 3
Classifier: Programming Language :: Python :: 3.11
Classifier: Programming Language :: Python :: 3.12
Classifier: Topic :: Scientific/Engineering :: Artificial Intelligence
Classifier: Topic :: Security
Classifier: Topic :: Software Development :: Libraries :: Python Modules
Requires-Python: >=3.11
Requires-Dist: aiosqlite>=0.19.0
Requires-Dist: alembic>=1.13.0
Requires-Dist: fastapi>=0.104.0
Requires-Dist: greenlet>=3.0.0
Requires-Dist: httpx>=0.25.0
Requires-Dist: motor>=3.3.0
Requires-Dist: numpy>=1.26.0
Requires-Dist: openai>=1.3.0
Requires-Dist: pandas>=2.1.0
Requires-Dist: passlib[bcrypt]>=1.7.4
Requires-Dist: pydantic-settings>=2.1.0
Requires-Dist: pydantic>=2.5.0
Requires-Dist: pymongo>=4.6.0
Requires-Dist: python-jose[cryptography]>=3.3.0
Requires-Dist: python-multipart>=0.0.6
Requires-Dist: redis>=5.0.0
Requires-Dist: scikit-learn>=1.3.0
Requires-Dist: sentence-transformers>=2.2.0
Requires-Dist: sqlalchemy>=2.0.23
Requires-Dist: torch>=2.1.0
Requires-Dist: transformers>=4.35.0
Requires-Dist: uvicorn[standard]>=0.24.0
Requires-Dist: websockets>=12.0
Provides-Extra: dev
Requires-Dist: black>=23.11.0; extra == 'dev'
Requires-Dist: mypy>=1.7.0; extra == 'dev'
Requires-Dist: pre-commit>=3.5.0; extra == 'dev'
Requires-Dist: pytest-asyncio>=0.21.1; extra == 'dev'
Requires-Dist: pytest>=7.4.3; extra == 'dev'
Requires-Dist: ruff>=0.1.6; extra == 'dev'
